davinci_resolve_api/DaVinci.py
davinci_resolve_api/Folder.py
davinci_resolve_api/Gallery.py
davinci_resolve_api/GalleryStillAlbum.py
davinci_resolve_api/MediaPool.py
davinci_resolve_api/MediaPoolItem.py
davinci_resolve_api/MediaStorage.py
davinci_resolve_api/Project.py
davinci_resolve_api/ProjectManager.py
davinci_resolve_api/Timeline.py
davinci_resolve_api/TimelineItem.py
davinci_resolve_api/__init__.py
davinci_resolve_api-0.3.0.dist-info/AUTHORS.rst
davinci_resolve_api-0.3.0.dist-info/LICENSE
davinci_resolve_api-0.3.0.dist-info/METADATA
davinci_resolve_api-0.3.0.dist-info/WHEEL
davinci_resolve_api-0.3.0.dist-info/top_level.txt
davinci_resolve_api-0.3.0.dist-info/RECORD
