Metadata-Version: 2.1
Name: davinci-resolve-api
Version: 0.3.0
Summary: DaVinci Resolve API
Home-page: https://github.com/GMarinow/davinci_resolve_api
Author: Georgi Marinov
Author-email: georgi.marinow@gmail.com
License: MIT license
Keywords: davinci_resolve_api
Platform: UNKNOWN
Classifier: Development Status :: 2 - Pre-Alpha
Classifier: Intended Audience :: Developers
Classifier: License :: OSI Approved :: MIT License
Classifier: Natural Language :: English
Classifier: Programming Language :: Python :: 3
Classifier: Programming Language :: Python :: 3.6
Requires-Python: >=3.6
